README.md
setup.py
bin/dossier
bin/dterm
descript/__init__.py
descript/__main__.py
descript/clients/__init__.py
descript/clients/charthop/__init__.py
descript/clients/charthop/__main__.py
descript/clients/fivetran/__init__.py
descript/clients/fivetran/__main__.py
descript/clients/fivetran/md.py
descript/clients/googlegroup/__init__.py
descript/clients/mode/__init__.py
descript/clients/mode/__main__.py
descript/clients/mode/models.py
descript/dbtcov/__init__.py
descript/dbtcov/__main__.py
descript/dossier/__init__.py
descript/dossier/__main__.py
descript/headerdoc/__init__.py
descript/headerdoc/__main__.py
descript/kpis/__init__.py
descript/kpis/doccov/__init__.py
descript/kpis/doccov/__main__.py
descript/schema/__init__.py
descript/schema/models.py
descript/schema/avro/__init__.py
descript/schema/dbml/__init__.py
descript/schema/dbt/__init__.py
descript/schema/ddl/__init__.py
descript/schema/erd/__init__.py
descript/schema/markdown/__init__.py
dterm/README.md
dterm/__init__.py
dterm/__main__.py
dterm.egg-info/PKG-INFO
dterm.egg-info/SOURCES.txt
dterm.egg-info/dependency_links.txt
dterm.egg-info/requires.txt
dterm.egg-info/top_level.txt
dterm/dbt/__init__.py
dterm/dbt/models.py
dterm/dbt/impact/__init__.py
dterm/models/__init__.py
dterm/models/exposures/__init__.py
dterm/sourcerer/README.md
dterm/sourcerer/__init__.py
dterm/sourcerer/__main__.py
sql_history/README.md
sql_history/__init__.py
sql_history/__main__.py