Metadata-Version: 2.1
Name: dterm
Version: 0.0.7
Summary: Data Engineering Terminal Scripts
Home-page: http://github.com/dave-inc/descript
Author: trevor grayson
Author-email: trevor@dave.com
License: MIT
Classifier: License :: OSI Approved :: MIT License
Classifier: Programming Language :: Python
Requires-Dist: networkx
Requires-Dist: jinja2
Requires-Dist: sqlglot
Requires-Dist: pyyaml
